Workbook

Sheet Étape 5 - Analyse
A1: Évaluation des concepts — SS-6
A2: Étape 5 : Analyse des solutions par caractéristiques voulues
A3: Fonction : Journaliser, horodater et protéger l'intégrité de la chaîne, de l'acquisition à l'affichage
A5: Projet jumeau numérique — SS-6 (lot L5) | F5: Solution préférée | J5: ALTERNATIVES
F6: =G29 -> 0.8925 | J6: =K29 -> 0.6925 | N6: =O29 -> 0.825
F7: Concept B : journal de données | J7: Concept A : journal d'événements | N7: Concept C : journal à deux niveaux
A8: Priorité | B8: No item | C8: Critère de décision | D8: Poids | F8: Niveau atteint | G8: Résultat pondéré | H8: Commentaires | J8: Niveau atteint | K8: Résultat pondéré | L8: Commentaires | N8: Niveau atteint | O8: Résultat pondéré | P8: Commentaires
B9: 1 | C9: F1. Refaire le diagnostic | D9: =SUM(D10:D12) -> 0.25 | F9: =IF(D9=0,0,G9/D9) -> 1 | G9: =SUM(G10:G12) -> 0.25 | J9: =IF(D9=0,0,K9/D9) -> 0.2 | K9: =SUM(K10:K12) -> 0.05 | N9: =IF(D9=0,0,O9/D9) -> 0.62 | O9: =SUM(O10:O12) -> 0.155
A10: 1 | B10: 1 | C10: Recalcul des décisions | D10: 0.12 | F10: 1 | G10: =F10*$D10 -> 0.12 | H10: Toute la campagne rejouée à l'identique | J10: 0.25 | K10: =J10*$D10 -> 0.03 | L10: Valeurs non écrites (empreinte seulement) : reconstitution seule tant que SS-1 n'a pas démontré EX-F-02 | N10: 0.75 | O10: =N10*$D10 -> 0.09 | P10: Recalcul limité à la fenêtre de 24 h du tampon
A11: 2 | B11: 2 | C11: Profondeur du recalcul | D11: 0.08 | F11: 1 | G11: =F11*$D11 -> 0.08 | H11: Campagne entière | J11: 0.25 | K11: =J11*$D11 -> 0.02 | L11: Aucune valeur conservée : moins de 24 h | N11: 0.5 | O11: =N11*$D11 -> 0.04 | P11: 24 h
A12: 2 | B12: 3 | C12: Indépendance de la vérification | D12: 0.05 | F12: 1 | G12: =F12*$D12 -> 0.05 | H12: Recalcul par un tiers sur toute la campagne | J12: 0 | K12: =J12*$D12 -> 0 | L12: Vérificateur indépendant de la chaîne, mais pas du diagnostic (rien à recalculer) | N12: 0.5 | O12: =N12*$D12 -> 0.025 | P12: Indépendante seulement sur la fenêtre de 24 h
B13: 2 | C13: F2. Prouver l'intégrité | D13: =SUM(D14:D16) -> 0.25 | F13: =IF(D13=0,0,G13/D13) -> 0.77 | G13: =SUM(G14:G16) -> 0.1925 | J13: =IF(D13=0,0,K13/D13) -> 0.77 | K13: =SUM(K14:K16) -> 0.1925 | N13: =IF(D13=0,0,O13/D13) -> 1 | O13: =SUM(O14:O16) -> 0.25
A14: 1 | B14: 4 | C14: Détection des altérations | D14: 0.12 | F14: 1 | G14: =F14*$D14 -> 0.12 | H14: Chaînage SHA-256 | J14: 1 | K14: =J14*$D14 -> 0.12 | L14: Chaînage HMAC-SHA-256 + scellement (1000 entrées / 5 min) | N14: 1 | O14: =N14*$D14 -> 0.12 | P14: Arbre de Merkle + signature ECDSA
A15: 2 | B15: 5 | C15: Coût de vérification | D15: 0.08 | F15: 0.75 | G15: =F15*$D15 -> 0.06 | H15: < 1 min mais croissant avec la durée | J15: 0.75 | K15: =J15*$D15 -> 0.06 | L15: Recalcul de toute la chaîne : < 1 min mais croissant | N15: 1 | O15: =N15*$D15 -> 0.08 | P15: Borné par bloc scellé
A16: 2 | B16: 6 | C16: Séparation des rôles | D16: 0.05 | F16: 0.25 | G16: =F16*$D16 -> 0.0125 | H16: Producteur détient la clé : limite écrite | J16: 0.25 | K16: =J16*$D16 -> 0.0125 | L16: Clé détenue par le producteur : limite écrite dans la spécification | N16: 1 | O16: =N16*$D16 -> 0.05 | P16: Sceau signé par un rôle distinct
B17: 3 | C17: F3. Temps et stockage | D17: =SUM(D18:D20) -> 0.2 | F17: =IF(D17=0,0,G17/D17) -> 0.75 | G17: =SUM(G18:G20) -> 0.15 | J17: =IF(D17=0,0,K17/D17) -> 0.75 | K17: =SUM(K18:K20) -> 0.15 | N17: =IF(D17=0,0,O17/D17) -> 0.775 | O17: =SUM(O18:O20) -> 0.155
A18: 1 | B18: 7 | C18: Surcoût par cycle | D18: 0.1 | F18: 0.75 | G18: =F18*$D18 -> 0.075 | H18: ≈ 3 % de T (estimé, à mesurer) | J18: 0.75 | K18: =J18*$D18 -> 0.075 | L18: ≈ 3 % de T estimé ; borne spécifiée ≤ 5 % au pire cas (EX-Q-01) | N18: 0.75 | O18: =N18*$D18 -> 0.075 | P18: ≈ 3 % de T (estimé, à mesurer)
A19: 2 | B19: 8 | C19: Volume sur 100 h | D19: 0.06 | F19: 0.75 | G19: =F19*$D19 -> 0.045 | H19: ≈ 1,4 Go (384 o × 10 cycles/s) | J19: 0.75 | K19: =J19*$D19 -> 0.045 | L19: ≤ 1,8 Go au pire (entrée bornée à 512 o × 10 cycles/s) | N19: 1 | O19: =N19*$D19 -> 0.06 | P19: ≈ 0,33 Go (24 h de données)
A20: 3 | B20: 9 | C20: Effort de réalisation | D20: 0.04 | F20: 0.75 | G20: =F20*$D20 -> 0.03 | H20: ≈ 40 h | J20: 0.75 | K20: =J20*$D20 -> 0.03 | L20: ≈ 40 h (chaîne, scellement, rotation, vérificateur) | N20: 0.5 | O20: =N20*$D20 -> 0.02 | P20: ≈ 80 h (deux structures + clé)
B21: 4 | C21: F4. Horodater et numéroter | D21: =SUM(D22:D24) -> 0.15 | F21: =IF(D21=0,0,G21/D21) -> 1 | G21: =SUM(G22:G24) -> 0.15 | J21: =IF(D21=0,0,K21/D21) -> 1 | K21: =SUM(K22:K24) -> 0.15 | N21: =IF(D21=0,0,O21/D21) -> 1 | O21: =SUM(O22:O24) -> 0.15
A22: 2 | B22: 10 | C22: Numéro de séquence | D22: 0.06 | F22: 1 | G22: =F22*$D22 -> 0.06 | H22: Continu | J22: 1 | K22: =J22*$D22 -> 0.06 | L22: Strictement croissant, jamais remis à zéro | N22: 1 | O22: =N22*$D22 -> 0.06 | P22: Continu
A23: 2 | B23: 11 | C23: Ordre garanti | D23: 0.05 | F23: 1 | G23: =F23*$D23 -> 0.05 | H23: Aucune inversion | J23: 1 | K23: =J23*$D23 -> 0.05 | L23: Un seul écrivain : ordre d'écriture = ordre des numéros | N23: 1 | O23: =N23*$D23 -> 0.05 | P23: Aucune inversion
A24: 3 | B24: 12 | C24: Double horodatage | D24: 0.04 | F24: 1 | G24: =F24*$D24 -> 0.04 | H24: Temps simulé et UTC | J24: 1 | K24: =J24*$D24 -> 0.04 | L24: Horodatage daté + horloge monotone + n° de cycle (temps simulé) | N24: 1 | O24: =N24*$D24 -> 0.04 | P24: Temps simulé et UTC
B25: 5 | C25: F5. Complétude | D25: =SUM(D26:D28) -> 0.15 | F25: =IF(D25=0,0,G25/D25) -> 1 | G25: =SUM(G26:G28) -> 0.15 | J25: =IF(D25=0,0,K25/D25) -> 1 | K25: =SUM(K26:K28) -> 0.15 | N25: =IF(D25=0,0,O25/D25) -> 0.76666667 | O25: =SUM(O26:O28) -> 0.115
A26: 2 | B26: 13 | C26: Complétude des acquisitions | D26: 0.08 | F26: 1 | G26: =F26*$D26 -> 0.08 | H26: Entrée par entrée | J26: 1 | K26: =J26*$D26 -> 0.08 | L26: 1 événement d'acquisition par cycle (EX-F-10) | N26: 0.75 | O26: =N26*$D26 -> 0.06 | P26: Par compteurs de bloc
A27: 3 | B27: 14 | C27: Complétude des décisions | D27: 0.04 | F27: 1 | G27: =F27*$D27 -> 0.04 | H27: Avec l'affichage | J27: 1 | K27: =J27*$D27 -> 0.04 | L27: Chaîne couverte jusqu'à l'affichage (9 types d'événements) | N27: 1 | O27: =N27*$D27 -> 0.04 | P27: Avec l'affichage
A28: 3 | B28: 15 | C28: Simplicité de la vérification | D28: 0.03 | F28: 1 | G28: =F28*$D28 -> 0.03 | H28: Un compte | J28: 1 | K28: =J28*$D28 -> 0.03 | L28: Un compte (continuité des numéros) | N28: 0.5 | O28: =N28*$D28 -> 0.015 | P28: Deux comptes à réconcilier
C29: TOTAL | D29: =D9+D13+D17+D21+D25 -> 1 | G29: =G9+G13+G17+G21+G25 -> 0.8925 | K29: =K9+K13+K17+K21+K25 -> 0.6925 | O29: =O9+O13+O17+O21+O25 -> 0.825
C31: Conditions éliminatoires (vérifiées avant pondération)
C32: Toutes les altérations sont détectées | F32: Oui | J32: Oui | N32: Oui
C33: Numéros de séquence continus (EX-Q-02) | F33: Oui | J33: Oui | N33: Oui
C34: Budget de temps du cycle respecté (EX-Q-01) | F34: Oui | J34: Oui | N34: Oui
C35: Aucune commande émise (EX-F-08) | F35: Oui | J35: Oui | N35: Oui
C36: Concept admissible ? | F36: =IF(COUNTIF(F32:F35,"Oui")=4,"Admissible","REJETÉ") -> Admissible | J36: =IF(COUNTIF(J32:J35,"Oui")=4,"Admissible","REJETÉ") -> Admissible | N36: =IF(COUNTIF(N32:N35,"Oui")=4,"Admissible","REJETÉ") -> Admissible
C37: Rang | F37: =RANK(G29,($G$29~$K$29~$O$29)) -> 1 | J37: =RANK(K29,($G$29~$K$29~$O$29)) -> 3 | N37: =RANK(O29,($G$29~$K$29~$O$29)) -> 2
A39: Décision : concept B retenu (rejeu complet du diagnostic), complété par le scellement périodique signé du concept C (séparation des rôles, ≈ 20 h de travail en plus).
A40: Résultat pondéré = niveau atteint × poids. Cellules bleues = valeurs saisies (modifiables) ; les totaux se recalculent.
A41: Niveaux B et C : repris de l'analyse quantitative SS-6. Niveaux A : évalués avec le même barème à partir des spécifications techniques du concept A (v0.1) — à valider en équipe.
A42: Priorité (1 à 3) : déduite du poids (≥ 10 → 1 ; 5 à 8 → 2 ; ≤ 4 → 3).
A43: Les niveaux sont estimés ; à confirmer par mesure, en particulier le surcoût par cycle.

Sheet Synthèse
A1: Résultat par fonctionnalité
A3: Fonctionnalité | B3: Poids | C3: Concept B | D3: Concept A | E3: Concept C | F3: Meilleur
A4: ='Étape 5 - Analyse'!C9 -> F1. Refaire le diagnostic | B4: ='Étape 5 - Analyse'!D9*100 -> 25 | C4: ='Étape 5 - Analyse'!G9*100 -> 25 | D4: ='Étape 5 - Analyse'!K9*100 -> 5 | E4: ='Étape 5 - Analyse'!O9*100 -> 15.5 | F4: =IF(COUNTIF(C4:E4,MAX(C4:E4))>1,"Égalité",INDEX($C$3:$E$3,MATCH(MAX(C4:E4),C4:E4,0))) -> Concept B
A5: ='Étape 5 - Analyse'!C13 -> F2. Prouver l'intégrité | B5: ='Étape 5 - Analyse'!D13*100 -> 25 | C5: ='Étape 5 - Analyse'!G13*100 -> 19.25 | D5: ='Étape 5 - Analyse'!K13*100 -> 19.25 | E5: ='Étape 5 - Analyse'!O13*100 -> 25 | F5: =IF(COUNTIF(C5:E5,MAX(C5:E5))>1,"Égalité",INDEX($C$3:$E$3,MATCH(MAX(C5:E5),C5:E5,0))) -> Concept C
A6: ='Étape 5 - Analyse'!C17 -> F3. Temps et stockage | B6: ='Étape 5 - Analyse'!D17*100 -> 20 | C6: ='Étape 5 - Analyse'!G17*100 -> 15 | D6: ='Étape 5 - Analyse'!K17*100 -> 15 | E6: ='Étape 5 - Analyse'!O17*100 -> 15.5 | F6: =IF(COUNTIF(C6:E6,MAX(C6:E6))>1,"Égalité",INDEX($C$3:$E$3,MATCH(MAX(C6:E6),C6:E6,0))) -> Concept C
A7: ='Étape 5 - Analyse'!C21 -> F4. Horodater et numéroter | B7: ='Étape 5 - Analyse'!D21*100 -> 15 | C7: ='Étape 5 - Analyse'!G21*100 -> 15 | D7: ='Étape 5 - Analyse'!K21*100 -> 15 | E7: ='Étape 5 - Analyse'!O21*100 -> 15 | F7: =IF(COUNTIF(C7:E7,MAX(C7:E7))>1,"Égalité",INDEX($C$3:$E$3,MATCH(MAX(C7:E7),C7:E7,0))) -> Égalité
A8: ='Étape 5 - Analyse'!C25 -> F5. Complétude | B8: ='Étape 5 - Analyse'!D25*100 -> 15 | C8: ='Étape 5 - Analyse'!G25*100 -> 15 | D8: ='Étape 5 - Analyse'!K25*100 -> 15 | E8: ='Étape 5 - Analyse'!O25*100 -> 11.5 | F8: =IF(COUNTIF(C8:E8,MAX(C8:E8))>1,"Égalité",INDEX($C$3:$E$3,MATCH(MAX(C8:E8),C8:E8,0))) -> Égalité
A9: ='Étape 5 - Analyse'!C29 -> TOTAL | B9: ='Étape 5 - Analyse'!D29*100 -> 100 | C9: ='Étape 5 - Analyse'!G29*100 -> 89.25 | D9: ='Étape 5 - Analyse'!K29*100 -> 69.25 | E9: ='Étape 5 - Analyse'!O29*100 -> 82.5 | F9: =IF(COUNTIF(C9:E9,MAX(C9:E9))>1,"Égalité",INDEX($C$3:$E$3,MATCH(MAX(C9:E9),C9:E9,0))) -> Concept B
A11: Points sur 100. Liens vers la feuille « Étape 5 - Analyse ».

Sheet Barèmes
A1: Critères, pondérations et barèmes
A3: Critère | B3: Poids | C3: Barème
A4: F1. Refaire le diagnostic | B4: 25
A5: Recalcul des décisions | B5: 12 | C5: Toute la campagne 100 % ; fenêtre récente 75 % ; reconstitution seule 25 %
A6: Profondeur du recalcul | B6: 8 | C6: Campagne 100 % ; 7 jours 75 % ; 24 h 50 % ; moins 25 %
A7: Indépendance de la vérification | B7: 5 | C7: Totale 100 % ; sur une fenêtre 50 % ; aucune 0 %
A8: F2. Prouver l'intégrité | B8: 25
A9: Détection des altérations | B9: 12 | C9: 100 % détectées 100 % ; sinon rejet
A10: Coût de vérification | B10: 8 | C10: Borné 100 % ; < 1 min mais croissant 75 % ; < 10 min 50 %
A11: Séparation des rôles | B11: 5 | C11: Sceau signé par un autre rôle 100 % ; limite écrite 25 % ; sinon rejet
A12: F3. Temps et stockage | B12: 20
A13: Surcoût par cycle | B13: 10 | C13: ≤ 1 % 100 % ; 3 % 75 % ; 5 % 50 % ; hors budget rejet
A14: Volume sur 100 h | B14: 6 | C14: ≤ 1 Go 100 % ; 10 Go 75 % ; 50 Go 25 %
A15: Effort de réalisation | B15: 4 | C15: 20 h 100 % ; 40 h 75 % ; 80 h 50 %
A16: F4. Horodater et numéroter | B16: 15
A17: Numéro de séquence | B17: 6 | C17: Continu 100 % ; trou possible rejet
A18: Ordre garanti | B18: 5 | C18: Aucune inversion 100 % ; inversions détectées 50 %
A19: Double horodatage | B19: 4 | C19: Temps simulé et UTC 100 % ; un seul 50 %
A20: F5. Complétude | B20: 15
A21: Complétude des acquisitions | B21: 8 | C21: Entrée par entrée 100 % ; par compteurs de bloc 75 %
A22: Complétude des décisions | B22: 4 | C22: Avec l'affichage 100 % ; sans 50 % ; incomplète rejet
A23: Simplicité de la vérification | B23: 3 | C23: Un compte 100 % ; deux comptes 50 %
A25: Hypothèses de volume : cycle de 100 ms ; 40 valeurs × 8 o + 64 o d'en-tête = 384 o/entrée (B) ; ≈ 13,8 Mo/h ; 100 h ≈ 1,4 Go (B), 0,33 Go (C, 24 h). A : entrée bornée à 512 o → ≤ 18,4 Mo/h, ≤ 1,8 Go/100 h.
